claim_master/__init__.py
claim_master/main.py
claim_master-1.0.0.dist-info/WHEEL
claim_master-1.0.0.dist-info/entry_points.txt
claim_master-1.0.0.dist-info/METADATA
claim_master-1.0.0.dist-info/RECORD
