Metadata-Version: 2.4
Name: claim-master
Version: 1.0.0
Summary: CLI to manage custom claims of Firebase users
License-Expression: GPL-3.0-or-later
Requires-Dist: firebase-admin>=7.1.0
Requires-Python: >=3.13
